{"card_name": "Elizabeth, Halloween Witch", "color": "BR", "rarity": "uncommon", "type": "Legendary Creature \u2013 Servant Caster", "number": 162, "color_identity": "BR", "cost": "{B}{R}", "rules_text": "Menace\nIf it\u2019s neither day nor night, it becomes day as this creature enters.\n[i]B\u00e1thory Halloween Erzs\u00e9bet \u2013[/i] When Elizabeth, Halloween Witch deals combat damage to a player, it becomes night.", "pt": "2/2", "special_text": "", "shape": "normal", "set": "FTE", "loyalty": "", "notes": ""}